AUTHORS.rst
CONTRIBUTING.rst
HISTORY.rst
LICENSE
MANIFEST.in
README.rst
setup.cfg
setup.py
docs/Makefile
docs/authors.rst
docs/conf.py
docs/contributing.rst
docs/history.rst
docs/index.rst
docs/installation.rst
docs/make.bat
docs/readme.rst
docs/usage.rst
kinparse/__init__.py
kinparse/kinparse.py
kinparse/pckg_info.py
kinparse/py_2_3.py
kinparse.egg-info/PKG-INFO
kinparse.egg-info/SOURCES.txt
kinparse.egg-info/dependency_links.txt
kinparse.egg-info/entry_points.txt
kinparse.egg-info/not-zip-safe
kinparse.egg-info/requires.txt
kinparse.egg-info/top_level.txt
tests/__init__.py
tests/setup_teardown.py
tests/test_kinparse.py
tests/data/control_board.net
tests/data/gaillard.net
tests/data/gardenlight.net
tests/data/kicad5_test.net
tests/data/kicad5_test.sch
tests/data/kicad6_test.kicad_sch
tests/data/kicad6_test.net
tests/data/kicad8_test.kicad_sch
tests/data/kicad8_test.net
tests/data/kicad9_test.kicad_sch
tests/data/kicad9_test.net
tests/data/ref2by2.net
tests/data/test.net
tests/data/test.py