Metadata-Version: 2.4
Name: kinparse
Version: 1.2.4
Summary: Parser for KiCad schematic netlists.
Home-page: https://github.com/devbisme/kinparse
Author: Dave Vandenbout
Author-email: devb@xess.com
License: MIT
Project-URL: Documentation, https://devbisme.github.io/kinparse
Project-URL: Source, https://github.com/devbisme/kinparse
Project-URL: Changelog, https://github.com/devbisme/kinparse/blob/master/HISTORY.rst
Project-URL: Tracker, https://github.com/devbisme/kinparse/issues
Keywords: kinparse KiCad netlist parsing
Classifier: Development Status :: 5 - Production/Stable
Classifier: Intended Audience :: Developers
Classifier: License :: OSI Approved :: MIT License
Classifier: Natural Language :: English
Classifier: Operating System :: OS Independent
Classifier: Programming Language :: Python :: 3
Classifier: Topic :: Scientific/Engineering :: Electronic Design Automation (EDA)
License-File: LICENSE
License-File: AUTHORS.rst
Requires-Dist: future>=0.15.0
Requires-Dist: pyparsing>=2.1.1
Dynamic: author
Dynamic: author-email
Dynamic: classifier
Dynamic: description
Dynamic: home-page
Dynamic: keywords
Dynamic: license
Dynamic: license-file
Dynamic: project-url
Dynamic: requires-dist
Dynamic: summary
